{
    "congestion": {
        "name": "Network Congestion",
        "description": "Simulates high traffic causing lag.",
        "color": "orange",
        "effects": {
            "latency": 150,
            "link_utilization": 95,
            "throughput": -500,
            "packet_loss": 2.5
        }
    },
    "ddos_attack": {
        "name": "DDoS Attack",
        "description": "Massive traffic spike and packet loss.",
        "color": "red",
        "effects": {
            "throughput": 5000,
            "packet_loss": 50.0,
            "latency": 300,
            "link_utilization": 100
        }
    },
    "firmware_corruption": {
        "name": "Firmware Corruption",
        "description": "Destabilizes device health and routing.",
        "color": "purple",
        "effects": {
            "packet_loss": 5.0,
            "device_health": "Critical", 
            "routing_status": "Flapping" 
        }
    },
    "fiber_cut": {
        "name": "Fiber Optic Cut",
        "description": "Complete physical link failure.",
        "color": "#34495e",
        "effects": {
            "throughput": -10000, 
            "packet_loss": 100,
            "routing_status": "Unreachable"
        }
    },
    "bgp_leak": {
        "name": "BGP Route Leak",
        "description": "Traffic misrouted to wrong peers.",
        "color": "#d35400",
        "effects": {
            "latency": 250,
            "packet_loss": 8.0,
            "routing_status": "Flapping",
            "throughput": -200
        }
    },
    "broadcast_storm": {
        "name": "Broadcast Storm",
        "description": "Layer 2 loop causing internal flooding.",
        "color": "#16a085",
        "effects": {
            "throughput": 2000,
            "packet_loss": 15.0,
            "device_health": "Degraded",
            "latency": 80
        }
    }
}